jupyterwebcatconnect/__init__.py
jupyterwebcatconnect/_version.py
jupyterwebcatconnect/handlers.py
jupyterwebcatconnect-1.0.1.data/data/etc/jupyter/jupyter_server_config.d/jupyterwebcatconnect.json
jupyterwebcatconnect-1.0.1.data/data/share/jupyter/labextensions/jupyterwebcatconnect/package.json
jupyterwebcatconnect-1.0.1.data/data/share/jupyter/labextensions/jupyterwebcatconnect/static/537.5af852b926d188b2de37.js
jupyterwebcatconnect-1.0.1.data/data/share/jupyter/labextensions/jupyterwebcatconnect/static/728.bb25cab8fa421a1fc3c2.js
jupyterwebcatconnect-1.0.1.data/data/share/jupyter/labextensions/jupyterwebcatconnect/static/remoteEntry.1c1b4656ede7918870df.js
jupyterwebcatconnect-1.0.1.data/data/share/jupyter/labextensions/jupyterwebcatconnect/static/style.js
jupyterwebcatconnect-1.0.1.data/data/share/jupyter/labextensions/jupyterwebcatconnect/static/third-party-licenses.json
jupyterwebcatconnect-1.0.1.data/data/share/jupyter/labextensions/jupyterwebcatconnect/install.json
jupyterwebcatconnect-1.0.1.dist-info/METADATA
jupyterwebcatconnect-1.0.1.dist-info/WHEEL
jupyterwebcatconnect-1.0.1.dist-info/licenses/LICENSE
jupyterwebcatconnect-1.0.1.dist-info/RECORD
