Metadata-Version: 2.1
Name: jupyterwebcatconnect
Version: 1.0.1
Summary: A JupyterLab extension to submit notebook to webcat.
Project-URL: Homepage, https://github.com/infovis-vt/webcatjupyterplugin
Project-URL: Bug Tracker, https://github.com/infovis-vt/webcatjupyterplugin/issues
Project-URL: Repository, https://github.com/infovis-vt/webcatjupyterplugin.git
Author-email: Rituraj Sharma <sharma.rituraj13@gmail.com>
License: BSD 3-Clause License
License-File: LICENSE
Classifier: Framework :: Jupyter
Classifier: Framework :: Jupyter :: JupyterLab
Classifier: Framework :: Jupyter :: JupyterLab :: 4
Classifier: Framework :: Jupyter :: JupyterLab :: Extensions
Classifier: Framework :: Jupyter :: JupyterLab :: Extensions :: Prebuilt
Classifier: License :: OSI Approved :: BSD License
Classifier: Programming Language :: Python
Classifier: Programming Language :: Python :: 3
Classifier: Programming Language :: Python :: 3.8
Classifier: Programming Language :: Python :: 3.9
Classifier: Programming Language :: Python :: 3.10
Classifier: Programming Language :: Python :: 3.11
Classifier: Programming Language :: Python :: 3.12
Requires-Python: >=3.8
Requires-Dist: jupyter-server<3,>=2.0.1
